pacmap/__init__.py
pacmap/pacmap.py
pacmap-0.7.6.dist-info/LICENSE
pacmap-0.7.6.dist-info/METADATA
pacmap-0.7.6.dist-info/WHEEL
pacmap-0.7.6.dist-info/top_level.txt
pacmap-0.7.6.dist-info/RECORD
