Metadata-Version: 2.1
Name: pacmap
Version: 0.7.6
Summary: The official implementation for PaCMAP: Pairwise Controlled Manifold Approximation Projection
Home-page: https://github.com/YingfanWang/PaCMAP
Author: Yingfan Wang, Haiyang Huang, Cynthia Rudin, Yaron Shaposhnik
Author-email: yingfan.wang@duke.edu
Project-URL: Bug Tracker, https://github.com/YingfanWang/PaCMAP/issues
Classifier: Programming Language :: Python :: 3
Classifier: License :: OSI Approved :: MIT License
Classifier: Operating System :: OS Independent
Classifier: License :: OSI Approved :: Apache Software License
Classifier: Intended Audience :: Science/Research
Classifier: Intended Audience :: Developers
Requires-Python: >=3.6
License-File: LICENSE
Requires-Dist: scikit-learn>=0.20
Requires-Dist: numba>=0.57
Requires-Dist: annoy>=1.11
Requires-Dist: numpy>=1.20
